scamper_pywarts-0.2.1.dist-info/DESCRIPTION.rst
scamper_pywarts-0.2.1.dist-info/METADATA
scamper_pywarts-0.2.1.dist-info/RECORD
scamper_pywarts-0.2.1.dist-info/WHEEL
scamper_pywarts-0.2.1.dist-info/metadata.json
scamper_pywarts-0.2.1.dist-info/top_level.txt
warts/__init__.py
warts/base.py
warts/cycle.py
warts/errors.py
warts/list.py
warts/parsing.py
warts/traceroute.py
