Metadata-Version: 1.1
Name: scamper-pywarts
Version: 0.2.1
Summary: Pure-python library allowing to read the Warts file format produced by Scamper (an Internet measurement tool from CAIDA)
Home-page: https://github.com/drakkar-lig/scamper-pywarts
Author: Baptiste Jonglez
Author-email: python@bitsofnetworks.org
License: MIT
Keywords: Internet measurement scamper warts traceroute ping
Platform: UNKNOWN
Classifier: Development Status :: 3 - Alpha
Classifier: Intended Audience :: Developers
Classifier: Intended Audience :: Science/Research
Classifier: Topic :: Internet
Classifier: Topic :: Scientific/Engineering
Classifier: License :: OSI Approved :: MIT License
Classifier: Programming Language :: Python :: 2
Classifier: Programming Language :: Python :: 3
